FPTE/FPTE
FPTE/FPTE_Analyze_Stress.py
FPTE/FPTE_Ensemble_Average_AIMD.py
FPTE/FPTE_RMSD.py
FPTE/FPTE_Result_Stress_2nd.py
FPTE/FPTE_Setup_VASP.py
FPTE/FPTE_clean.py
FPTE/__init__.py
FPTE/_min_dependencies.py
FPTE/exceptions.py
FPTE-1.2.1.data/scripts/FPTE
tests/__init__.py
tests/FPTE/__init__.py
tests/FPTE/test_FPTE_Analyze_Stress.py
tests/FPTE/test_FPTE_RMSD.py
tests/FPTE/test_FPTE_Result_Stress_2nd.py
tests/FPTE/test_FPTE_Setup_VASP.py
tests/FPTE/test_FPTE_clean.py
FPTE-1.2.1.dist-info/LICENSE
FPTE-1.2.1.dist-info/METADATA
FPTE-1.2.1.dist-info/WHEEL
FPTE-1.2.1.dist-info/top_level.txt
FPTE-1.2.1.dist-info/RECORD
