Metadata-Version: 2.1
Name: FPTE
Version: 1.2.1
Summary: The FPTE package is a collection of tools for finite pressure temperature elastic constants calculation. Features include, but are not limited to stress-strain method for getting second order elastic tensors using DFT package VASP as well as, ab initio molecular dynamic method for temperaturedependent elastic constants.
Home-page: https://github.com/MahdiDavari/FPTE
Download-URL: https://pypi.org/project/FPTE/#files
Author: Mahdi Davari
Author-email: Mahdi.Davari@iCloud.com
License: UNKNOWN
Project-URL: Documentation, https://github.com/MahdiDavari/FPTE/blob/master/README.md
Project-URL: Source Code, https://github.com/MahdiDavari/FPTE
Project-URL: Bug Reports, https://github.com/MahdiDavari/FPTE/issues
Platform: UNKNOWN
Classifier: Intended Audience :: Science/Research
Classifier: Intended Audience :: Developers
Classifier: Programming Language :: Python
Classifier: Topic :: Software Development
Classifier: Topic :: Scientific/Engineering
Classifier: Development Status :: 5 - Production/Stable
Classifier: Operating System :: POSIX
Classifier: Operating System :: Unix
Classifier: Operating System :: MacOS
Classifier: Programming Language :: Python :: 3
Classifier: Programming Language :: Python :: 3.7
Classifier: Programming Language :: Python :: 3.8
Classifier: Programming Language :: Python :: 3.9
Classifier: Programming Language :: Python :: 3.10
Classifier: Programming Language :: Python :: Implementation :: CPython
Classifier: License :: OSI Approved :: MIT License
Classifier: Operating System :: OS Independent
Requires-Python: >=3.7
License-File: LICENSE
Requires-Dist: numpy (>=1.16.5)
Requires-Dist: pandas (>=0.25.3)
Requires-Dist: matplotlib (>=2.2.4)
Requires-Dist: joblib (>=0.11)
Requires-Dist: subprocess32 (>=3.5.4)
Provides-Extra: docs
Requires-Dist: pandas (>=0.25.3) ; extra == 'docs'
Requires-Dist: matplotlib (>=2.2.4) ; extra == 'docs'
Requires-Dist: seaborn (>=0.9.0) ; extra == 'docs'
Requires-Dist: memory-profiler (>=0.57.0) ; extra == 'docs'
Requires-Dist: sphinx (>=4.0.1) ; extra == 'docs'
Requires-Dist: sphinx-gallery (>=0.7.0) ; extra == 'docs'
Requires-Dist: Pillow (>=7.1.2) ; extra == 'docs'
Requires-Dist: sphinx-prompt (>=1.3.0) ; extra == 'docs'
Requires-Dist: sphinxext-opengraph (>=0.4.2) ; extra == 'docs'
Provides-Extra: examples
Requires-Dist: pandas (>=0.25.3) ; extra == 'examples'
Requires-Dist: matplotlib (>=2.2.4) ; extra == 'examples'
Requires-Dist: seaborn (>=0.9.0) ; extra == 'examples'
Provides-Extra: tests
Requires-Dist: pandas (>=0.25.3) ; extra == 'tests'
Requires-Dist: matplotlib (>=2.2.4) ; extra == 'tests'
Requires-Dist: pytest (>=5.0.1) ; extra == 'tests'
Requires-Dist: PyHamcrest (>=2.0.3) ; extra == 'tests'
Requires-Dist: pytest-cov (>=2.9.0) ; extra == 'tests'
Requires-Dist: pyamg (>=4.0.0) ; extra == 'tests'
